mkdocs_backlinks_section_plugin/__init__.py
mkdocs_backlinks_section_plugin-0.0.9.dist-info/licenses/LICENSE
mkdocs_backlinks_section_plugin-0.0.9.dist-info/METADATA
mkdocs_backlinks_section_plugin-0.0.9.dist-info/WHEEL
mkdocs_backlinks_section_plugin-0.0.9.dist-info/entry_points.txt
mkdocs_backlinks_section_plugin-0.0.9.dist-info/top_level.txt
mkdocs_backlinks_section_plugin-0.0.9.dist-info/RECORD
