Metadata-Version: 2.4
Name: mkdocs-backlinks-section-plugin
Version: 0.0.9
Summary: Adds a backlinks section that lists every page linking to the current page.
Home-page: https://github.com/six-two/mkdocs-backlinks-section-plugin
Author: six-two
Author-email: pip@six-two.dev
License: MIT License
Classifier: License :: OSI Approved :: MIT License
Classifier: Operating System :: POSIX :: Linux
Classifier: Programming Language :: Python :: 3
Classifier: Programming Language :: Python :: 3.9
Classifier: Programming Language :: Python :: 3.10
Classifier: Programming Language :: Python :: 3.11
Classifier: Programming Language :: Python :: 3.12
Classifier: Programming Language :: Python :: 3.13
Requires-Python: >=3.9
License-File: LICENSE
Requires-Dist: mkdocs>=1.5.0
Dynamic: license-file
